[
  {
    "Car": {
      "Make": "Toyota",
      "Model": "Yaris",
      "TravelledDistance": 94775807
    },
    "CustomerName": "Daniele Zarate",
    "Discount": "20%",
    "Price": 588.51,
    "PriceWithDiscount": 470.808000
  },
  {
    "Car": {
      "Make": "Ford",
      "Model": "Pinto",
      "TravelledDistance": 2147647
    },
    "CustomerName": "Natalie Poli",
    "Discount": "40%",
    "Price": 3703.65,
    "PriceWithDiscount": 2222.190000
  },
  {
    "Car": {
      "Make": "Peugeot",
      "Model": "206",
      "TravelledDistance": 21474647
    },
    "CustomerName": "Sylvie Mcelravy",
    "Discount": "10%",
    "Price": 350.97,
    "PriceWithDiscount": 315.873000
  },
  {
    "Car": {
      "Make": "BMW",
      "Model": "F04",
      "TravelledDistance": 100000
    },
    "CustomerName": "Ann Mcenaney",
    "Discount": "40%",
    "Price": 316.91,
    "PriceWithDiscount": 180.63870000
  },
  {
    "Car": {
      "Make": "Opel",
      "Model": "Omega",
      "TravelledDistance": 2147483647
    },
    "CustomerName": "Carri Knapik",
    "Discount": "10%",
    "Price": 1576.96,
    "PriceWithDiscount": 1348.30080000
  },
  {
    "Car": {
      "Make": "Nissan",
      "Model": "Versa",
      "TravelledDistance": 922775807
    },
    "CustomerName": "Francis Mckim",
    "Discount": "20%",
    "Price": 1156.71,
    "PriceWithDiscount": 879.09960000
  },
  {
    "Car": {
      "Make": "Nissan",
      "Model": "370Z",
      "TravelledDistance": 922775807
    },
    "CustomerName": "Marcelle Griego",
    "Discount": "10%",
    "Price": 3202.97,
    "PriceWithDiscount": 2738.53935000
  },
  {
    "Car": {
      "Make": "Fiat",
      "Model": "500L",
      "TravelledDistance": 922337204775807
    },
    "CustomerName": "Marcelle Griego",
    "Discount": "15%",
    "Price": 1223.32,
    "PriceWithDiscount": 987.83090000
  },
  {
    "Car": {
      "Make": "Chevy",
      "Model": "Malibu",
      "TravelledDistance": 922337775807
    },
    "CustomerName": "Hai Everton",
    "Discount": "40%",
    "Price": 1474.95,
    "PriceWithDiscount": 840.72150000
  },
  {
    "Car": {
      "Make": "Peugeot",
      "Model": "407",
      "TravelledDistance": 9223372775807
    },
    "CustomerName": "Rico Peer",
    "Discount": "5%",
    "Price": 627.97,
    "PriceWithDiscount": 566.74292500
  },
  {
    "Car": {
      "Make": "Citroen",
      "Model": "C4",
      "TravelledDistance": 213647
    },
    "CustomerName": "Kristian Engberg",
    "Discount": "0%",
    "Price": 229.96,
    "PriceWithDiscount": 229.960000
  },
  {
    "Car": {
      "Make": "Lamborghini",
      "Model": "Diablo",
      "TravelledDistance": 2147483647
    },
    "CustomerName": "Carole Witman",
    "Discount": "5%",
    "Price": 4333.96,
    "PriceWithDiscount": 4117.262000
  },
  {
    "Car": {
      "Make": "Rolls-Royce",
      "Model": "Phantom Drophead Coupé",
      "TravelledDistance": 9223372075807
    },
    "CustomerName": "Rico Peer",
    "Discount": "5%",
    "Price": 1495.45,
    "PriceWithDiscount": 1349.64362500
  },
  {
    "Car": {
      "Make": "Toyota",
      "Model": "Camry Hybrid",
      "TravelledDistance": 954775807
    },
    "CustomerName": "Teddy Hobby",
    "Discount": "5%",
    "Price": 2612.96,
    "PriceWithDiscount": 2358.19640000
  },
  {
    "Car": {
      "Make": "BMW",
      "Model": "M Roadster E85",
      "TravelledDistance": 92233720365807
    },
    "CustomerName": "Ann Mcenaney",
    "Discount": "30%",
    "Price": 801.95,
    "PriceWithDiscount": 533.29675000
  },
  {
    "Car": {
      "Make": "Ford",
      "Model": "Ranger",
      "TravelledDistance": 92233775807
    },
    "CustomerName": "Nisha Markwell",
    "Discount": "50%",
    "Price": 319.30,
    "PriceWithDiscount": 159.650000
  },
  {
    "Car": {
      "Make": "Nissan",
      "Model": "Altima",
      "TravelledDistance": 2147483647
    },
    "CustomerName": "Hai Everton",
    "Discount": "50%",
    "Price": 513.52,
    "PriceWithDiscount": 243.92200000
  },
  {
    "Car": {
      "Make": "Nissan",
      "Model": "Altima",
      "TravelledDistance": 2147
    },
    "CustomerName": "Zada Attwood",
    "Discount": "50%",
    "Price": 322.97,
    "PriceWithDiscount": 153.41075000
  },
  {
    "Car": {
      "Make": "Opel",
      "Model": "Omega",
      "TravelledDistance": 1
    },
    "CustomerName": "Garret Capron",
    "Discount": "5%",
    "Price": 435.61,
    "PriceWithDiscount": 413.829500
  },
  {
    "Car": {
      "Make": "Opel",
      "Model": "Astra",
      "TravelledDistance": 922337203685807
    },
    "CustomerName": "Rema Revelle",
    "Discount": "30%",
    "Price": 1410.22,
    "PriceWithDiscount": 937.79630000
  },
  {
    "Car": {
      "Make": "Fiat",
      "Model": "Freemont",
      "TravelledDistance": 214647
    },
    "CustomerName": "Marcelle Griego",
    "Discount": "20%",
    "Price": 1253.22,
    "PriceWithDiscount": 952.44720000
  },
  {
    "Car": {
      "Make": "Ferrari",
      "Model": "Daytona",
      "TravelledDistance": 213647
    },
    "CustomerName": "Louann Holzworth",
    "Discount": "30%",
    "Price": 267.97,
    "PriceWithDiscount": 187.579000
  },
  {
    "Car": {
      "Make": "Seat",
      "Model": "Toledo",
      "TravelledDistance": 21447
    },
    "CustomerName": "Daniele Zarate",
    "Discount": "0%",
    "Price": 322.97,
    "PriceWithDiscount": 322.970000
  },
  {
    "Car": {
      "Make": "Toyota",
      "Model": "Prius",
      "TravelledDistance": 922335807
    },
    "CustomerName": "Rico Peer",
    "Discount": "15%",
    "Price": 1729.89,
    "PriceWithDiscount": 1396.88617500
  },
  {
    "Car": {
      "Make": "Ferrari",
      "Model": "F430",
      "TravelledDistance": 214647
    },
    "CustomerName": "Zada Attwood",
    "Discount": "0%",
    "Price": 372.90,
    "PriceWithDiscount": 354.25500000
  },
  {
    "Car": {
      "Make": "Rolls-Royce",
      "Model": "Ghost",
      "TravelledDistance": 21473647
    },
    "CustomerName": "Nisha Markwell",
    "Discount": "20%",
    "Price": 1339.96,
    "PriceWithDiscount": 1071.968000
  },
  {
    "Car": {
      "Make": "Peugeot",
      "Model": "306",
      "TravelledDistance": 21474647
    },
    "CustomerName": "Cinthia Lasala",
    "Discount": "15%",
    "Price": 4228.15,
    "PriceWithDiscount": 3414.23112500
  },
  {
    "Car": {
      "Make": "Fiat",
      "Model": "500L",
      "TravelledDistance": 92233754775807
    },
    "CustomerName": "Yvonne Mccalla",
    "Discount": "5%",
    "Price": 123.28,
    "PriceWithDiscount": 111.26020000
  },
  {
    "Car": {
      "Make": "Seat",
      "Model": "Ibiza",
      "TravelledDistance": 21474847
    },
    "CustomerName": "Lino Subia",
    "Discount": "50%",
    "Price": 322.88,
    "PriceWithDiscount": 161.440000
  },
  {
    "Car": {
      "Make": "Opel",
      "Model": "Kadet",
      "TravelledDistance": 21474847
    },
    "CustomerName": "Cinthia Lasala",
    "Discount": "50%",
    "Price": 1312.96,
    "PriceWithDiscount": 623.65600000
  },
  {
    "Car": {
      "Make": "Mercedes",
      "Model": "W124",
      "TravelledDistance": 2147647
    },
    "CustomerName": "Jimmy Grossi",
    "Discount": "20%",
    "Price": 1476.91,
    "PriceWithDiscount": 1122.45160000
  },
  {
    "Car": {
      "Make": "Toyota",
      "Model": "Camry Hybrid",
      "TravelledDistance": 214647
    },
    "CustomerName": "Sylvie Mcelravy",
    "Discount": "0%",
    "Price": 1416.95,
    "PriceWithDiscount": 1416.950000
  },
  {
    "Car": {
      "Make": "BMW",
      "Model": "M6 E63",
      "TravelledDistance": 92235807
    },
    "CustomerName": "Hipolito Lamoreaux",
    "Discount": "5%",
    "Price": 1249.97,
    "PriceWithDiscount": 1128.09792500
  },
  {
    "Car": {
      "Make": "Nissan",
      "Model": "370Z",
      "TravelledDistance": 922307
    },
    "CustomerName": "Garret Capron",
    "Discount": "10%",
    "Price": 2306.96,
    "PriceWithDiscount": 2076.264000
  },
  {
    "Car": {
      "Make": "Seat",
      "Model": "Mii",
      "TravelledDistance": 214747
    },
    "CustomerName": "Brett Brickley",
    "Discount": "15%",
    "Price": 602.27,
    "PriceWithDiscount": 486.33302500
  },
  {
    "Car": {
      "Make": "Peugeot",
      "Model": "206",
      "TravelledDistance": 214748347
    },
    "CustomerName": "Francis Mckim",
    "Discount": "30%",
    "Price": 249.97,
    "PriceWithDiscount": 166.23005000
  },
  {
    "Car": {
      "Make": "Toyota",
      "Model": "Corolla",
      "TravelledDistance": 21477
    },
    "CustomerName": "Lino Subia",
    "Discount": "0%",
    "Price": 1143.98,
    "PriceWithDiscount": 1143.980000
  },
  {
    "Car": {
      "Make": "Peugeot",
      "Model": "407",
      "TravelledDistance": 854775807
    },
    "CustomerName": "Daniele Zarate",
    "Discount": "50%",
    "Price": 233.91,
    "PriceWithDiscount": 116.955000
  },
  {
    "Car": {
      "Make": "Fiat",
      "Model": "500L",
      "TravelledDistance": 922337203675807
    },
    "CustomerName": "Emmitt Benally",
    "Discount": "40%",
    "Price": 698.31,
    "PriceWithDiscount": 398.03670000
  },
  {
    "Car": {
      "Make": "Fiat",
      "Model": "Panda",
      "TravelledDistance": 2147487
    },
    "CustomerName": "Carole Witman",
    "Discount": "10%",
    "Price": 327.96,
    "PriceWithDiscount": 295.164000
  },
  {
    "Car": {
      "Make": "Citroen",
      "Model": "Elysée",
      "TravelledDistance": 922354775807
    },
    "CustomerName": "Kristian Engberg",
    "Discount": "20%",
    "Price": 277.96,
    "PriceWithDiscount": 222.368000
  },
  {
    "Car": {
      "Make": "Citroen",
      "Model": "C1",
      "TravelledDistance": 9854775807
    },
    "CustomerName": "Hai Everton",
    "Discount": "50%",
    "Price": 180.91,
    "PriceWithDiscount": 85.93225000
  },
  {
    "Car": {
      "Make": "Peugeot",
      "Model": "306",
      "TravelledDistance": 2147483647
    },
    "CustomerName": "Kristian Engberg",
    "Discount": "15%",
    "Price": 293.88,
    "PriceWithDiscount": 249.798000
  },
  {
    "Car": {
      "Make": "Ferrari",
      "Model": "Daytona",
      "TravelledDistance": 922337275807
    },
    "CustomerName": "Sylvie Mcelravy",
    "Discount": "20%",
    "Price": 385.46,
    "PriceWithDiscount": 308.368000
  },
  {
    "Car": {
      "Make": "Mercedes",
      "Model": "W210",
      "TravelledDistance": 9223372036854775807
    },
    "CustomerName": "Brett Brickley",
    "Discount": "40%",
    "Price": 318.96,
    "PriceWithDiscount": 181.80720000
  },
  {
    "Car": {
      "Make": "Nissan",
      "Model": "Altima",
      "TravelledDistance": 213647
    },
    "CustomerName": "Rema Revelle",
    "Discount": "40%",
    "Price": 2887.65,
    "PriceWithDiscount": 1645.96050000
  },
  {
    "Car": {
      "Make": "Chevy",
      "Model": "Camaro",
      "TravelledDistance": 922335807
    },
    "CustomerName": "Audrea Cardinal",
    "Discount": "20%",
    "Price": 335.80,
    "PriceWithDiscount": 268.640000
  },
  {
    "Car": {
      "Make": "Peugeot",
      "Model": "206",
      "TravelledDistance": 922775807
    },
    "CustomerName": "Louann Holzworth",
    "Discount": "40%",
    "Price": 334.96,
    "PriceWithDiscount": 200.976000
  },
  {
    "Car": {
      "Make": "Renault",
      "Model": "Captur",
      "TravelledDistance": 92233724775807
    },
    "CustomerName": "Emmitt Benally",
    "Discount": "20%",
    "Price": 355.47,
    "PriceWithDiscount": 270.15720000
  },
  {
    "Car": {
      "Make": "Opel",
      "Model": "Corsa",
      "TravelledDistance": 2
    },
    "CustomerName": "Johnette Derryberry",
    "Discount": "30%",
    "Price": 1111.32,
    "PriceWithDiscount": 739.02780000
  },
  {
    "Car": {
      "Make": "Peugeot",
      "Model": "407",
      "TravelledDistance": 922036854775807
    },
    "CustomerName": "Carri Knapik",
    "Discount": "20%",
    "Price": 538.95,
    "PriceWithDiscount": 409.60200000
  },
  {
    "Car": {
      "Make": "Peugeot",
      "Model": "206",
      "TravelledDistance": 2147483647
    },
    "CustomerName": "Hipolito Lamoreaux",
    "Discount": "50%",
    "Price": 285.06,
    "PriceWithDiscount": 135.40350000
  },
  {
    "Car": {
      "Make": "Skoda",
      "Model": "Citigo",
      "TravelledDistance": 2183647
    },
    "CustomerName": "Carole Witman",
    "Discount": "15%",
    "Price": 594.52,
    "PriceWithDiscount": 505.342000
  },
  {
    "Car": {
      "Make": "Alfa Romeo",
      "Model": "164",
      "TravelledDistance": 92233775807
    },
    "CustomerName": "Garret Capron",
    "Discount": "40%",
    "Price": 1767.09,
    "PriceWithDiscount": 1060.254000
  },
  {
    "Car": {
      "Make": "Skoda",
      "Model": "Citigo",
      "TravelledDistance": 92233854775807
    },
    "CustomerName": "Francis Mckim",
    "Discount": "40%",
    "Price": 229.97,
    "PriceWithDiscount": 131.08290000
  },
  {
    "Car": {
      "Make": "Dacia",
      "Model": "Dokker",
      "TravelledDistance": 213647
    },
    "CustomerName": "Lino Subia",
    "Discount": "15%",
    "Price": 784.96,
    "PriceWithDiscount": 667.216000
  },
  {
    "Car": {
      "Make": "Skoda",
      "Model": "Fabia",
      "TravelledDistance": 9223372036875808
    },
    "CustomerName": "Audrea Cardinal",
    "Discount": "15%",
    "Price": 276.96,
    "PriceWithDiscount": 235.416000
  },
  {
    "Car": {
      "Make": "BMW",
      "Model": "F20",
      "TravelledDistance": 21447
    },
    "CustomerName": "Carole Witman",
    "Discount": "10%",
    "Price": 1390.31,
    "PriceWithDiscount": 1251.279000
  },
  {
    "Car": {
      "Make": "Chevy",
      "Model": "Impala",
      "TravelledDistance": 214747
    },
    "CustomerName": "Emmitt Benally",
    "Discount": "30%",
    "Price": 782.32,
    "PriceWithDiscount": 520.24280000
  },
  {
    "Car": {
      "Make": "Ferrari",
      "Model": "Daytona",
      "TravelledDistance": 92036854775807
    },
    "CustomerName": "Lino Subia",
    "Discount": "20%",
    "Price": 432.53,
    "PriceWithDiscount": 346.024000
  },
  {
    "Car": {
      "Make": "BMW",
      "Model": "M6 E63",
      "TravelledDistance": 214747
    },
    "CustomerName": "Kristian Engberg",
    "Discount": "0%",
    "Price": 1204.99,
    "PriceWithDiscount": 1204.990000
  },
  {
    "Car": {
      "Make": "Ferrari",
      "Model": "F430",
      "TravelledDistance": 92236854775807
    },
    "CustomerName": "Lino Subia",
    "Discount": "10%",
    "Price": 4269.90,
    "PriceWithDiscount": 3842.910000
  },
  {
    "Car": {
      "Make": "Toyota",
      "Model": "Corolla",
      "TravelledDistance": 2147
    },
    "CustomerName": "Zada Attwood",
    "Discount": "50%",
    "Price": 296.39,
    "PriceWithDiscount": 140.78525000
  },
  {
    "Car": {
      "Make": "Mercedes",
      "Model": "W212",
      "TravelledDistance": 2147647
    },
    "CustomerName": "Johnette Derryberry",
    "Discount": "30%",
    "Price": 2409.96,
    "PriceWithDiscount": 1602.62340000
  },
  {
    "Car": {
      "Make": "BMW",
      "Model": "F25",
      "TravelledDistance": 9223372036854775807
    },
    "CustomerName": "Oren Perlman",
    "Discount": "10%",
    "Price": 408.53,
    "PriceWithDiscount": 349.29315000
  },
  {
    "Car": {
      "Make": "Toyota",
      "Model": "Tacoma",
      "TravelledDistance": 247
    },
    "CustomerName": "Francis Mckim",
    "Discount": "15%",
    "Price": 235.88,
    "PriceWithDiscount": 190.47310000
  },
  {
    "Car": {
      "Make": "Nissan",
      "Model": "GT-R",
      "TravelledDistance": 2147447
    },
    "CustomerName": "Carri Knapik",
    "Discount": "15%",
    "Price": 255.97,
    "PriceWithDiscount": 206.69577500
  },
  {
    "Car": {
      "Make": "Citroen",
      "Model": "Berlingo",
      "TravelledDistance": 9223354775807
    },
    "CustomerName": "Brett Brickley",
    "Discount": "5%",
    "Price": 1049.06,
    "PriceWithDiscount": 946.77665000
  },
  {
    "Car": {
      "Make": "BMW",
      "Model": "F04",
      "TravelledDistance": 483647
    },
    "CustomerName": "Carole Witman",
    "Discount": "10%",
    "Price": 1172.37,
    "PriceWithDiscount": 1055.133000
  },
  {
    "Car": {
      "Make": "Nissan",
      "Model": "GT-R",
      "TravelledDistance": 2143647
    },
    "CustomerName": "Johnette Derryberry",
    "Discount": "5%",
    "Price": 3670.65,
    "PriceWithDiscount": 3312.76162500
  },
  {
    "Car": {
      "Make": "Toyota",
      "Model": "Corolla",
      "TravelledDistance": 9223807
    },
    "CustomerName": "Cinthia Lasala",
    "Discount": "30%",
    "Price": 82.97,
    "PriceWithDiscount": 55.17505000
  },
  {
    "Car": {
      "Make": "Mercedes",
      "Model": "W212",
      "TravelledDistance": 54775807
    },
    "CustomerName": "Audrea Cardinal",
    "Discount": "15%",
    "Price": 481.63,
    "PriceWithDiscount": 409.385500
  },
  {
    "Car": {
      "Make": "Renault",
      "Model": "Clio IV",
      "TravelledDistance": 2147483647
    },
    "CustomerName": "Faustina Burgher",
    "Discount": "10%",
    "Price": 408.95,
    "PriceWithDiscount": 368.055000
  },
  {
    "Car": {
      "Make": "Toyota",
      "Model": "Tacoma",
      "TravelledDistance": 9225807
    },
    "CustomerName": "Cinthia Lasala",
    "Discount": "15%",
    "Price": 2744.95,
    "PriceWithDiscount": 2216.54712500
  },
  {
    "Car": {
      "Make": "Mercedes",
      "Model": "W211",
      "TravelledDistance": 47757
    },
    "CustomerName": "Lino Subia",
    "Discount": "50%",
    "Price": 584.98,
    "PriceWithDiscount": 292.490000
  },
  {
    "Car": {
      "Make": "BMW",
      "Model": "E88",
      "TravelledDistance": 200000
    },
    "CustomerName": "Francis Mckim",
    "Discount": "5%",
    "Price": 588.63,
    "PriceWithDiscount": 531.23857500
  },
  {
    "Car": {
      "Make": "Rolls-Royce",
      "Model": "Wraith",
      "TravelledDistance": 2147483647
    },
    "CustomerName": "Louann Holzworth",
    "Discount": "15%",
    "Price": 692.86,
    "PriceWithDiscount": 588.931000
  },
  {
    "Car": {
      "Make": "Ferrari",
      "Model": "275",
      "TravelledDistance": 214647
    },
    "CustomerName": "Carole Witman",
    "Discount": "10%",
    "Price": 288.97,
    "PriceWithDiscount": 260.073000
  },
  {
    "Car": {
      "Make": "Citroen",
      "Model": "C1",
      "TravelledDistance": 922337854775807
    },
    "CustomerName": "Nisha Markwell",
    "Discount": "30%",
    "Price": 2402.97,
    "PriceWithDiscount": 1682.079000
  },
  {
    "Car": {
      "Make": "Skoda",
      "Model": "Rapid",
      "TravelledDistance": 2147447
    },
    "CustomerName": "Hipolito Lamoreaux",
    "Discount": "20%",
    "Price": 5642.51,
    "PriceWithDiscount": 4288.30760000
  },
  {
    "Car": {
      "Make": "Ford",
      "Model": "GT40",
      "TravelledDistance": 9223377
    },
    "CustomerName": "Sylvie Mcelravy",
    "Discount": "20%",
    "Price": 1628.23,
    "PriceWithDiscount": 1302.584000
  },
  {
    "Car": {
      "Make": "Mercedes",
      "Model": "W211",
      "TravelledDistance": 922775807
    },
    "CustomerName": "Taina Achenbach",
    "Discount": "5%",
    "Price": 1556.64,
    "PriceWithDiscount": 1478.808000
  },
  {
    "Car": {
      "Make": "Peugeot",
      "Model": "405",
      "TravelledDistance": 92036854775807
    },
    "CustomerName": "Cinthia Lasala",
    "Discount": "0%",
    "Price": 3202.23,
    "PriceWithDiscount": 3042.11850000
  },
  {
    "Car": {
      "Make": "Toyota",
      "Model": "Tacoma",
      "TravelledDistance": 96854775807
    },
    "CustomerName": "Brett Brickley",
    "Discount": "30%",
    "Price": 488.81,
    "PriceWithDiscount": 325.05865000
  },
  {
    "Car": {
      "Make": "Skoda",
      "Model": "Fabia",
      "TravelledDistance": 922337203775807
    },
    "CustomerName": "Taina Achenbach",
    "Discount": "30%",
    "Price": 2010.88,
    "PriceWithDiscount": 1407.616000
  },
  {
    "Car": {
      "Make": "Seat",
      "Model": "Mii",
      "TravelledDistance": 92236854775807
    },
    "CustomerName": "Rema Revelle",
    "Discount": "10%",
    "Price": 456.16,
    "PriceWithDiscount": 390.01680000
  },
  {
    "Car": {
      "Make": "Opel",
      "Model": "Corsa",
      "TravelledDistance": 21474847
    },
    "CustomerName": "Brett Brickley",
    "Discount": "40%",
    "Price": 321.98,
    "PriceWithDiscount": 183.52860000
  },
  {
    "Car": {
      "Make": "Ford",
      "Model": "GT40",
      "TravelledDistance": 92233775807
    },
    "CustomerName": "Natalie Poli",
    "Discount": "20%",
    "Price": 291.29,
    "PriceWithDiscount": 233.032000
  },
  {
    "Car": {
      "Make": "Renault",
      "Model": "Alaskan",
      "TravelledDistance": 92807
    },
    "CustomerName": "Hipolito Lamoreaux",
    "Discount": "5%",
    "Price": 347.84,
    "PriceWithDiscount": 313.92560000
  },
  {
    "Car": {
      "Make": "Peugeot",
      "Model": "405",
      "TravelledDistance": 9226854775807
    },
    "CustomerName": "Jimmy Grossi",
    "Discount": "40%",
    "Price": 202.89,
    "PriceWithDiscount": 115.64730000
  }
]